nmdc_runtime/client/__init__.py
nmdc_runtime/client/main.py
nmdc_runtime_client-0.1.0.dist-info/METADATA
nmdc_runtime_client-0.1.0.dist-info/WHEEL
nmdc_runtime_client-0.1.0.dist-info/entry_points.txt
nmdc_runtime_client-0.1.0.dist-info/top_level.txt
nmdc_runtime_client-0.1.0.dist-info/RECORD
